Metadata-Version: 2.1
Name: dictschema
Version: 0.0.1
Summary: Schema validation for python dictionaries
Home-page: https://github.com/kbeauregard/dictschema
Author: Kyle Beauregard
Author-email: kylembeauregard@gmail.com
License: MIT
Keywords: dict,schema,validation
Platform: UNKNOWN
Classifier: Programming Language :: Python :: 3
Classifier: Programming Language :: Python :: 3.7
Classifier: Operating System :: OS Independent
